ft_cli/__init__.py
ft_cli/main.py
ft_cli-0.1.0.dist-info/entry_points.txt
ft_cli-0.1.0.dist-info/WHEEL
ft_cli-0.1.0.dist-info/METADATA
ft_cli-0.1.0.dist-info/RECORD
